vatify/__init__.py
vatify/cli.py
vatify/client.py
vatify-0.1.5.dist-info/METADATA
vatify-0.1.5.dist-info/WHEEL
vatify-0.1.5.dist-info/entry_points.txt
vatify-0.1.5.dist-info/licenses/LICENSE
vatify-0.1.5.dist-info/RECORD
