Metadata-Version: 2.4
Name: vatify
Version: 0.1.5
Summary: Official Python SDK for Vatify — EU VAT validation, rates, and calculation.
Project-URL: Homepage, https://vatifytax.app
Project-URL: Documentation, https://vatifytax.app
Project-URL: Repository, https://github.com/vatifytax/vatify-python
Project-URL: Issues, https://github.com/vatifytax/vatify-python/issues
Author: Vatify Team
License: MIT
License-File: LICENSE
Keywords: API,EU VAT,VAT,rates,tax,validation
Classifier: Intended Audience :: Developers
Classifier: License :: OSI Approved :: MIT License
Classifier: Programming Language :: Python :: 3
Classifier: Topic :: Internet :: WWW/HTTP
Classifier: Topic :: Office/Business :: Financial :: Accounting
Classifier: Typing :: Typed
Requires-Python: >=3.9
Requires-Dist: httpx>=0.27.0
Requires-Dist: pydantic>=2.8.0
